dir2clip/__init__.py
dir2clip/core.py
dir2clip-0.1.3.dist-info/licenses/LICENSE
dir2clip-0.1.3.dist-info/METADATA
dir2clip-0.1.3.dist-info/WHEEL
dir2clip-0.1.3.dist-info/entry_points.txt
dir2clip-0.1.3.dist-info/top_level.txt
dir2clip-0.1.3.dist-info/RECORD
