Metadata-Version: 2.4
Name: dir2clip
Version: 0.1.3
Summary: A CLI tool to flatten directory contents to clipboard for LLM context.
Home-page: https://github.com/alextereshyt/Dir2Clip
Author: alextereshyt
Author-email: alextereshyt@gmail.com
Classifier: Programming Language :: Python :: 3
Classifier: License :: OSI Approved :: MIT License
Classifier: Operating System :: OS Independent
Requires-Python: >=3.6
License-File: LICENSE
Requires-Dist: pyperclip
Dynamic: author
Dynamic: author-email
Dynamic: classifier
Dynamic: description
Dynamic: description-content-type
Dynamic: home-page
Dynamic: license-file
Dynamic: requires-dist
Dynamic: requires-python
Dynamic: summary
